churn_prediction/__init__.py
churn_prediction/config.py
churn_prediction/dataset.py
churn_prediction/experiments.py
churn_prediction/features.py
churn_prediction/models/__init__.py
churn_prediction/models/predict.py
churn_prediction/models/train.py
churn_prediction/tests/test_features.py
churn_prediction-0.1.0.dist-info/METADATA
churn_prediction-0.1.0.dist-info/WHEEL
churn_prediction-0.1.0.dist-info/RECORD
