Metadata-Version: 2.1
Name: churn_prediction
Version: 0.1.0
Summary: Pacote para previsão de churn
Author: Daniele
Requires-Python: >=3.12,<4.0
Classifier: Programming Language :: Python :: 3
Classifier: Programming Language :: Python :: 3.12
Classifier: Programming Language :: Python :: 3.13
Requires-Dist: black (>=24.10.0,<25.0.0)
Requires-Dist: imbalanced-learn (>=0.13.0,<0.14.0)
Requires-Dist: lightgbm (>=4.5.0,<5.0.0)
Requires-Dist: mlflow (>=2.19.0,<3.0.0)
Requires-Dist: openpyxl (>=3.1.5,<4.0.0)
Requires-Dist: pylint (>=3.3.3,<4.0.0)
Requires-Dist: pytest (>=8.3.4,<9.0.0)
Requires-Dist: scikit-learn (==1.5.2)
Requires-Dist: xgboost (>=2.1.3,<3.0.0)
